[{"kind": "youtube#commentThread", "etag": "qchFB8Ao2p7w3tOpNpGN_v-UZ6w", "id": "UgikiqxtPZMbE3gCoAEC", "snippet": {"videoId": "718qcWPzvAY", "topLevelComment": {"kind": "youtube#comment", "etag": "_AKT1GrAAWyF5zOt3gokDS9D77Y", "id": "UgikiqxtPZMbE3gCoAEC", "snippet": {"videoId": "718qcWPzvAY", "textDisplay": "Such memories with this game. This is especially a memorable theme, giving off that perfect \"near the end of a journey\" feel.", "textOriginal": "Such memories with this game. This is especially a memorable theme, giving off that perfect \"near the end of a journey\" feel.", "authorDisplayName": "Aegis29", "authorProfileImageUrl": "https://yt3.ggpht.com/a/AATXAJxDr8y4XLhMMYsYzgootu2Neq8BBe47bdBNoQICKg=s48-c-k-c0xffffffff-no-rj-mo", "authorChannelUrl": "http://www.youtube.com/channel/UCKymmHM7V0jHeyZAK4qFVZg", "authorChannelId": {"value": "UCKymmHM7V0jHeyZAK4qFVZg"}, "canRate": true, "viewerRating": "none", "likeCount": 1, "publishedAt": "2016-11-04T13:22:07Z", "updatedAt": "2016-11-04T13:22:07Z"}}, "canReply": true, "totalReplyCount": 1, "isPublic": true}, "replies": {"comments": [{"kind": "youtube#comment", "etag": "lhAv2-uGnbIUHZ8DO4BT9GIDC6s", "id": "UgikiqxtPZMbE3gCoAEC.8KrSDWlDYbG8KrSWLxrz2h", "snippet": {"textDisplay": "(Just noticed I had already commented on the video. Whoops.)", "textOriginal": "(Just noticed I had already commented on the video. Whoops.)", "parentId": "UgikiqxtPZMbE3gCoAEC", "authorDisplayName": "Aegis29", "authorProfileImageUrl": "https://yt3.ggpht.com/a/AATXAJxDr8y4XLhMMYsYzgootu2Neq8BBe47bdBNoQICKg=s48-c-k-c0xffffffff-no-rj-mo", "authorChannelUrl": "http://www.youtube.com/channel/UCKymmHM7V0jHeyZAK4qFVZg", "authorChannelId": {"value": "UCKymmHM7V0jHeyZAK4qFVZg"}, "canRate": true, "viewerRating": "none", "likeCount": 0, "publishedAt": "2016-11-04T13:24:41Z", "updatedAt": "2016-11-04T13:24:41Z"}}]}}, {"kind": "youtube#commentThread", "etag": "hEa2arH0uZb2tKtxJdGFGTLpkpM", "id": "UghEVt_-rdkAXHgCoAEC", "snippet": {"videoId": "718qcWPzvAY", "topLevelComment": {"kind": "youtube#comment", "etag": "HiL0akuHIql9y2TwsuuLM3qPZNs", "id": "UghEVt_-rdkAXHgCoAEC", "snippet": {"videoId": "718qcWPzvAY", "textDisplay": "You know what? I actually wouldn't mind another Paper Mario game in this game's style. As long as the story is good, the humor is fresh, it gives a decent challenge, and it expands upon SPM's core gameplay.", "textOriginal": "You know what? I actually wouldn't mind another Paper Mario game in this game's style. As long as the story is good, the humor is fresh, it gives a decent challenge, and it expands upon SPM's core gameplay.", "authorDisplayName": "Colton Riffle", "authorProfileImageUrl": "https://yt3.ggpht.com/a/AATXAJxmV4Bs-jysTW3ZjmwQpAx2yXh4vxfOb-Y9bZkoSw=s48-c-k-c0xffffffff-no-rj-mo", "authorChannelUrl": "http://www.youtube.com/channel/UCs6yebl8CFQAdXmMzeBdCzg", "authorChannelId": {"value": "UCs6yebl8CFQAdXmMzeBdCzg"}, "canRate": true, "viewerRating": "none", "likeCount": 3, "publishedAt": "2016-09-23T06:03:21Z", "updatedAt": "2016-09-23T06:03:21Z"}}, "canReply": true, "totalReplyCount": 0, "isPublic": true}}, {"kind": "youtube#commentThread", "etag": "1nXGD-Oqurwk57zKn7yAY0ftmzQ", "id": "UggFYoPImoTV0ngCoAEC", "snippet": {"videoId": "718qcWPzvAY", "topLevelComment": {"kind": "youtube#comment", "etag": "Bepug4AINb0UGULRKFM6j0Md3zk", "id": "UggFYoPImoTV0ngCoAEC", "snippet": {"videoId": "718qcWPzvAY", "textDisplay": "I think Bleck succeeded in destroying all worlds. Everything feels empty in the Paper Mario universe now.", "textOriginal": "I think Bleck succeeded in destroying all worlds. Everything feels empty in the Paper Mario universe now.", "authorDisplayName": "H Nickel", "authorProfileImageUrl": "https://yt3.ggpht.com/a/AATXAJzdMydy0fItPjKoxCMKJlcS_gXPd-0jEv8Gv27yuA=s48-c-k-c0xffffffff-no-rj-mo", "authorChannelUrl": "http://www.youtube.com/channel/UCmO6Q3kNl7U1d2oLANoth5g", "authorChannelId": {"value": "UCmO6Q3kNl7U1d2oLANoth5g"}, "canRate": true, "viewerRating": "none", "likeCount": 0, "publishedAt": "2016-07-23T00:56:11Z", "updatedAt": "2016-07-23T00:56:11Z"}}, "canReply": true, "totalReplyCount": 0, "isPublic": true}}, {"kind": "youtube#commentThread", "etag": "4tbACPqRR132624ckiM0eC3cnfE", "id": "UgjFcPA4fyCdLHgCoAEC", "snippet": {"videoId": "718qcWPzvAY", "topLevelComment": {"kind": "youtube#comment", "etag": "t2TzVgtmUaKA88CNnKR9j-ZLU_0", "id": "UgjFcPA4fyCdLHgCoAEC", "snippet": {"videoId": "718qcWPzvAY", "textDisplay": "I always read this as 'Castle Black' and think of Game of Thrones", "textOriginal": "I always read this as 'Castle Black' and think of Game of Thrones", "authorDisplayName": "StevenTravelCaptainRogers", "authorProfileImageUrl": "https://yt3.ggpht.com/a/AATXAJx0sUdxk697rS5VnioXPyc-wczPPFq79TNuktGC=s48-c-k-c0xffffffff-no-rj-mo", "authorChannelUrl": "http://www.youtube.com/channel/UCICgh48ZTAz0eBo49IlVXCA", "authorChannelId": {"value": "UCICgh48ZTAz0eBo49IlVXCA"}, "canRate": true, "viewerRating": "none", "likeCount": 2, "publishedAt": "2016-07-04T00:03:48Z", "updatedAt": "2016-08-29T19:43:41Z"}}, "canReply": true, "totalReplyCount": 0, "isPublic": true}}, {"kind": "youtube#commentThread", "etag": "TjWNTtmerAKEnmjrKcIiknleuYI", "id": "Ugj_h5eoKR_p1ngCoAEC", "snippet": {"videoId": "718qcWPzvAY", "topLevelComment": {"kind": "youtube#comment", "etag": "zOr3-ih8VQW69HywwgykQosP_a8", "id": "Ugj_h5eoKR_p1ngCoAEC", "snippet": {"videoId": "718qcWPzvAY", "textDisplay": "\"I found it surprisingly beautiful. In a brutal, horribly uncomfortable sort of way.\" Tyrion Lannister to Janos Slyn", "textOriginal": "\"I found it surprisingly beautiful. In a brutal, horribly uncomfortable sort of way.\" Tyrion Lannister to Janos Slyn", "authorDisplayName": "Dat Indigoku", "authorProfileImageUrl": "https://yt3.ggpht.com/a/AATXAJwrZye2wTIO55lr12fa3vwGlx5xdpuzzpaAmsm8=s48-c-k-c0xffffffff-no-rj-mo", "authorChannelUrl": "http://www.youtube.com/channel/UCOIiwwGtU3XPejIllbyyEBg", "authorChannelId": {"value": "UCOIiwwGtU3XPejIllbyyEBg"}, "canRate": true, "viewerRating": "none", "likeCount": 1, "publishedAt": "2016-06-30T20:46:38Z", "updatedAt": "2016-06-30T20:46:38Z"}}, "canReply": true, "totalReplyCount": 0, "isPublic": true}}, {"kind": "youtube#commentThread", "etag": "e9Ib2mpCMVIdO2jvBv4yXQqB53c", "id": "UgjUcWNIXlyG_XgCoAEC", "snippet": {"videoId": "718qcWPzvAY", "topLevelComment": {"kind": "youtube#comment", "etag": "7q6FE2iMnww13BACnixIIgvUQl0", "id": "UgjUcWNIXlyG_XgCoAEC", "snippet": {"videoId": "718qcWPzvAY", "textDisplay": "It was such a fun game! Glad I took the risk (same goes for Sticker Star, there are a lot of very FUN moments in sticker star, well worth the 15 bucks I payed for it!)", "textOriginal": "It was such a fun game! Glad I took the risk (same goes for Sticker Star, there are a lot of very FUN moments in sticker star, well worth the 15 bucks I payed for it!)", "authorDisplayName": "garfreeek", "authorProfileImageUrl": "https://yt3.ggpht.com/a/AATXAJz4q2ULGL6TFdXYC1Ul7AuE9dU3Z4ysO1H8LCm_=s48-c-k-c0xffffffff-no-rj-mo", "authorChannelUrl": "http://www.youtube.com/channel/UCjrQ-xNez_Yf2Ip9yPkaPiA", "authorChannelId": {"value": "UCjrQ-xNez_Yf2Ip9yPkaPiA"}, "canRate": true, "viewerRating": "none", "likeCount": 2, "publishedAt": "2016-06-30T19:20:28Z", "updatedAt": "2016-06-30T19:20:28Z"}}, "canReply": true, "totalReplyCount": 0, "isPublic": true}}, {"kind": "youtube#commentThread", "etag": "CxrrQlhjtx_QAhVAnklIEOoBXU8", "id": "UgjfUUABJsiUc3gCoAEC", "snippet": {"videoId": "718qcWPzvAY", "topLevelComment": {"kind": "youtube#comment", "etag": "i_vC2KGSsGK5pMQyaINQLCnkvhM", "id": "UgjfUUABJsiUc3gCoAEC", "snippet": {"videoId": "718qcWPzvAY", "textDisplay": "There are only toads now, bleck.", "textOriginal": "There are only toads now, bleck.", "authorDisplayName": "Sephiko", "authorProfileImageUrl": "https://yt3.ggpht.com/a/AATXAJzH3C9HEMABN5TN2DXvKqRQC2nN6CJ8IT6xSZAMXQ=s48-c-k-c0xffffffff-no-rj-mo", "authorChannelUrl": "http://www.youtube.com/channel/UCvker5CjSg6pNxAfSIbbbdw", "authorChannelId": {"value": "UCvker5CjSg6pNxAfSIbbbdw"}, "canRate": true, "viewerRating": "none", "likeCount": 4, "publishedAt": "2016-06-30T17:27:21Z", "updatedAt": "2016-06-30T17:27:21Z"}}, "canReply": true, "totalReplyCount": 0, "isPublic": true}}, {"kind": "youtube#commentThread", "etag": "54Ov1DT4Kv0Iq9CAvXe0ieuhCHE", "id": "Ugh9VF7mIM1o13gCoAEC", "snippet": {"videoId": "718qcWPzvAY", "topLevelComment": {"kind": "youtube#comment", "etag": "GxWAtNzL_Z84JZyslnFiZ_kTYt8", "id": "Ugh9VF7mIM1o13gCoAEC", "snippet": {"videoId": "718qcWPzvAY", "textDisplay": "Hey, atleast we got the Mario & Luigi series...", "textOriginal": "Hey, atleast we got the Mario & Luigi series...", "authorDisplayName": "Konata Izumi", "authorProfileImageUrl": "https://yt3.ggpht.com/a/AATXAJyYS0VXXaOnkRNQVmeVJWKMnjhLF2TtvC6DhHdsow=s48-c-k-c0xffffffff-no-rj-mo", "authorChannelUrl": "http://www.youtube.com/channel/UCvTshObPYylMT6A0lu15yuw", "authorChannelId": {"value": "UCvTshObPYylMT6A0lu15yuw"}, "canRate": true, "viewerRating": "none", "likeCount": 2, "publishedAt": "2016-06-30T16:20:14Z", "updatedAt": "2016-06-30T16:20:14Z"}}, "canReply": true, "totalReplyCount": 1, "isPublic": true}, "replies": {"comments": [{"kind": "youtube#comment", "etag": "pFyHwBVn-uJqdZQyQ50SqB88HS0", "id": "Ugh9VF7mIM1o13gCoAEC.8FkkdyJCzne9-gkTVJGniK", "snippet": {"textDisplay": "Oof", "textOriginal": "Oof", "parentId": "Ugh9VF7mIM1o13gCoAEC", "authorDisplayName": "SuperSavajin", "authorProfileImageUrl": "https://yt3.ggpht.com/a/AATXAJzrJslhI3Oq0rPwh56aKKqDObaMFlL3_EVdGB0-Hg=s48-c-k-c0xffffffff-no-rj-mo", "authorChannelUrl": "http://www.youtube.com/channel/UCydM_EQbgdt3Ghag8CB7tDA", "authorChannelId": {"value": "UCydM_EQbgdt3Ghag8CB7tDA"}, "canRate": true, "viewerRating": "none", "likeCount": 1, "publishedAt": "2019-10-05T04:08:37Z", "updatedAt": "2019-10-05T04:08:37Z"}}]}}, {"kind": "youtube#commentThread", "etag": "V89KRapl8AtxBn8sTEV6Kjk_79c", "id": "UghsaXAAG36Yq3gCoAEC", "snippet": {"videoId": "718qcWPzvAY", "topLevelComment": {"kind": "youtube#comment", "etag": "_us5EyqJJyyq-HHBc1x3NP7fBUk", "id": "UghsaXAAG36Yq3gCoAEC", "snippet": {"videoId": "718qcWPzvAY", "textDisplay": "SPM has such good music :3", "textOriginal": "SPM has such good music :3", "authorDisplayName": "Mellowship", "authorProfileImageUrl": "https://yt3.ggpht.com/a/AATXAJy8IidLpdqU68gWmWnqUxsoNplROwBHq-CKsAx4qA=s48-c-k-c0xffffffff-no-rj-mo", "authorChannelUrl": "http://www.youtube.com/channel/UCOagOqDR4Hbtb8FL5y5_Ylg", "authorChannelId": {"value": "UCOagOqDR4Hbtb8FL5y5_Ylg"}, "canRate": true, "viewerRating": "none", "likeCount": 3, "publishedAt": "2016-06-30T11:53:44Z", "updatedAt": "2016-06-30T11:53:44Z"}}, "canReply": true, "totalReplyCount": 0, "isPublic": true}}, {"kind": "youtube#commentThread", "etag": "TS6b0kuUBj4DgmCDHNDafO8yeE4", "id": "Ugh10NhMVfSVQHgCoAEC", "snippet": {"videoId": "718qcWPzvAY", "topLevelComment": {"kind": "youtube#comment", "etag": "EA_roHyfTFZZAG6a_YWK9m0K32c", "id": "Ugh10NhMVfSVQHgCoAEC", "snippet": {"videoId": "718qcWPzvAY", "textDisplay": "Good game. Would've been great if they got someone to edit those atrociously long dialogue scenes.", "textOriginal": "Good game. Would've been great if they got someone to edit those atrociously long dialogue scenes.", "authorDisplayName": "Jay DiNItto", "authorProfileImageUrl": "https://yt3.ggpht.com/a/AATXAJy0Lm3_U2KrUpZt5Ry56OYXRhKxL_2gVOfs9HPCaw=s48-c-k-c0xffffffff-no-rj-mo", "authorChannelUrl": "http://www.youtube.com/channel/UCaCZjnx2GLsNVlIqHZJwMAw", "authorChannelId": {"value": "UCaCZjnx2GLsNVlIqHZJwMAw"}, "canRate": true, "viewerRating": "none", "likeCount": 0, "publishedAt": "2016-06-30T03:56:59Z", "updatedAt": "2016-06-30T03:56:59Z"}}, "canReply": true, "totalReplyCount": 0, "isPublic": true}}, {"kind": "youtube#commentThread", "etag": "kBM9Wxb2fgTInii3Lb_kKmLpFUg", "id": "UgiJBJQyoeLiE3gCoAEC", "snippet": {"videoId": "718qcWPzvAY", "topLevelComment": {"kind": "youtube#comment", "etag": "5t7-qaHEoB6iJ8mhNh2Fv-PYKwc", "id": "UgiJBJQyoeLiE3gCoAEC", "snippet": {"videoId": "718qcWPzvAY", "textDisplay": "The clock ticking at certain parts of the song really adds to the atmosphere and overall tone of the game during the castle levels...now I have the urge to play this game again (absolutely love it as well; feel it doesn't get the props it deserves when people flat out don't acknowledge it when talking about the series)", "textOriginal": "The clock ticking at certain parts of the song really adds to the atmosphere and overall tone of the game during the castle levels...now I have the urge to play this game again (absolutely love it as well; feel it doesn't get the props it deserves when people flat out don't acknowledge it when talking about the series)", "authorDisplayName": "Capitalist", "authorProfileImageUrl": "https://yt3.ggpht.com/a/AATXAJzJ2isvt1DACsTVThCN9w0jOumCqcBkY24HnDg6=s48-c-k-c0xffffffff-no-rj-mo", "authorChannelUrl": "http://www.youtube.com/channel/UCHUHwqfLqgU0DAQwsoiAEyA", "authorChannelId": {"value": "UCHUHwqfLqgU0DAQwsoiAEyA"}, "canRate": true, "viewerRating": "none", "likeCount": 6, "publishedAt": "2016-06-30T02:06:21Z", "updatedAt": "2016-06-30T02:06:21Z"}}, "canReply": true, "totalReplyCount": 0, "isPublic": true}}, {"kind": "youtube#commentThread", "etag": "haURqf57X41kG4aXLXN2VhRfwLA", "id": "UghrTA2gb23LIHgCoAEC", "snippet": {"videoId": "718qcWPzvAY", "topLevelComment": {"kind": "youtube#comment", "etag": "kFfYlTmhNbLzqKI1b3x-wFVP-rs", "id": "UghrTA2gb23LIHgCoAEC", "snippet": {"videoId": "718qcWPzvAY", "textDisplay": "I love Super Paper Mario so much. Thanks for yet again reminding me how much I love this game. :3", "textOriginal": "I love Super Paper Mario so much. Thanks for yet again reminding me how much I love this game. :3", "authorDisplayName": "Aegis29", "authorProfileImageUrl": "https://yt3.ggpht.com/a/AATXAJxDr8y4XLhMMYsYzgootu2Neq8BBe47bdBNoQICKg=s48-c-k-c0xffffffff-no-rj-mo", "authorChannelUrl": "http://www.youtube.com/channel/UCKymmHM7V0jHeyZAK4qFVZg", "authorChannelId": {"value": "UCKymmHM7V0jHeyZAK4qFVZg"}, "canRate": true, "viewerRating": "none", "likeCount": 2, "publishedAt": "2016-06-30T01:59:11Z", "updatedAt": "2016-06-30T01:59:11Z"}}, "canReply": true, "totalReplyCount": 0, "isPublic": true}}, {"kind": "youtube#commentThread", "etag": "Jze0kdTWMQUqprToM66ZLmF7Pcg", "id": "UgjREkGbIJohC3gCoAEC", "snippet": {"videoId": "718qcWPzvAY", "topLevelComment": {"kind": "youtube#comment", "etag": "zQXPcJM1YGuBZPlMS5ynXzT5pTs", "id": "UgjREkGbIJohC3gCoAEC", "snippet": {"videoId": "718qcWPzvAY", "textDisplay": "Ahhh, this is one of my favorite final level themes in any game, for sure.", "textOriginal": "Ahhh, this is one of my favorite final level themes in any game, for sure.", "authorDisplayName": "Jonochrome", "authorProfileImageUrl": "https://yt3.ggpht.com/a/AATXAJxp9xaIOMH8lmzwNKuk99-zP-Tqgi2pTv63Uly6=s48-c-k-c0xffffffff-no-rj-mo", "authorChannelUrl": "http://www.youtube.com/channel/UCI8Tzu6hyRrNvHczfyPr3FA", "authorChannelId": {"value": "UCI8Tzu6hyRrNvHczfyPr3FA"}, "canRate": true, "viewerRating": "none", "likeCount": 4, "publishedAt": "2016-06-30T01:09:57Z", "updatedAt": "2016-06-30T01:09:57Z"}}, "canReply": true, "totalReplyCount": 0, "isPublic": true}}, {"kind": "youtube#commentThread", "etag": "mftrkbX_RqJllP56uBRZDDkUsUY", "id": "UghEa6rssvK593gCoAEC", "snippet": {"videoId": "718qcWPzvAY", "topLevelComment": {"kind": "youtube#comment", "etag": "1xBXblu7q2UnQSY_ByxL9FyMMXA", "id": "UghEa6rssvK593gCoAEC", "snippet": {"videoId": "718qcWPzvAY", "textDisplay": "The last song to ever be heard before paper mario died.", "textOriginal": "The last song to ever be heard before paper mario died.", "authorDisplayName": "Mr.Ridley", "authorProfileImageUrl": "https://yt3.ggpht.com/a/AATXAJwsvyCPeyt7usX05Pd5bNCsHFrA40kKTJp30Ycn=s48-c-k-c0xffffffff-no-rj-mo", "authorChannelUrl": "http://www.youtube.com/channel/UCYHk8r0r6jy2_94z4NdmGqA", "authorChannelId": {"value": "UCYHk8r0r6jy2_94z4NdmGqA"}, "canRate": true, "viewerRating": "none", "likeCount": 10, "publishedAt": "2016-06-30T00:10:36Z", "updatedAt": "2016-06-30T00:10:36Z"}}, "canReply": true, "totalReplyCount": 2, "isPublic": true}, "replies": {"comments": [{"kind": "youtube#comment", "etag": "okPPaizBYrWApBtHhdut50mJXts", "id": "UghEa6rssvK593gCoAEC.8Fj0gDvIXBn8v3pe-J4MAm", "snippet": {"textDisplay": "@NoveltyHat ok.", "textOriginal": "@NoveltyHat ok.", "parentId": "UghEa6rssvK593gCoAEC", "authorDisplayName": "Knightmare007", "authorProfileImageUrl": "https://yt3.ggpht.com/a/AATXAJxbFie-2UIYYvT1EiQrB0XAEfjNs9QaBX6hifIXiw=s48-c-k-c0xffffffff-no-rj-mo", "authorChannelUrl": "http://www.youtube.com/channel/UCZWD8LGeulI1W4Qof2pIgyA", "authorChannelId": {"value": "UCZWD8LGeulI1W4Qof2pIgyA"}, "canRate": true, "viewerRating": "none", "likeCount": 0, "publishedAt": "2019-05-18T09:27:17Z", "updatedAt": "2019-05-18T09:27:17Z"}}, {"kind": "youtube#comment", "etag": "hkQK_JKMwU6V_0W3dLo5ucLSQbk", "id": "UghEa6rssvK593gCoAEC.8Fj0gDvIXBn8FoJz6DDxno", "snippet": {"textDisplay": "didn't care for this one to be honest", "textOriginal": "didn't care for this one to be honest", "parentId": "UghEa6rssvK593gCoAEC", "authorDisplayName": "NoveltyHat", "authorProfileImageUrl": "https://yt3.ggpht.com/a/AATXAJyk8uUIaAqS_tCp-d-XiaqHllhAb9d-tbCK3WnA=s48-c-k-c0xffffffff-no-rj-mo", "authorChannelUrl": "http://www.youtube.com/channel/UCwurFkI1qo_I_Gc68MvI3uw", "authorChannelId": {"value": "UCwurFkI1qo_I_Gc68MvI3uw"}, "canRate": true, "viewerRating": "none", "likeCount": 1, "publishedAt": "2016-07-02T01:35:24Z", "updatedAt": "2016-07-02T01:35:24Z"}}]}}, {"kind": "youtube#commentThread", "etag": "mCdV4zrCoZeQwVTsW-GT4EQbpKk", "id": "UghVNP8pHEfcYHgCoAEC", "snippet": {"videoId": "718qcWPzvAY", "topLevelComment": {"kind": "youtube#comment", "etag": "oHAGSPP7M2lD_Fvx4lw5pnRhBIc", "id": "UghVNP8pHEfcYHgCoAEC", "snippet": {"videoId": "718qcWPzvAY", "textDisplay": "Keep up the great work Supra!", "textOriginal": "Keep up the great work Supra!", "authorDisplayName": "Leonhart", "authorProfileImageUrl": "https://yt3.ggpht.com/a/AATXAJzdopl7CGjbff28a0ICM_a5_tf56CWhnGStIgcqYA=s48-c-k-c0xffffffff-no-rj-mo", "authorChannelUrl": "http://www.youtube.com/channel/UCBHD6Yg8R1yS9akfGm4mecQ", "authorChannelId": {"value": "UCBHD6Yg8R1yS9akfGm4mecQ"}, "canRate": true, "viewerRating": "none", "likeCount": 2, "publishedAt": "2016-06-30T00:04:07Z", "updatedAt": "2016-06-30T00:04:07Z"}}, "canReply": true, "totalReplyCount": 0, "isPublic": true}}, {"kind": "youtube#commentThread", "etag": "b_ziPjgyyspqk3aIQmYfVcL0fSs", "id": "UgjBLmJaD9nH53gCoAEC", "snippet": {"videoId": "718qcWPzvAY", "topLevelComment": {"kind": "youtube#comment", "etag": "wUQyjloa-GzlzwHsr1kX-RlkLwg", "id": "UgjBLmJaD9nH53gCoAEC", "snippet": {"videoId": "718qcWPzvAY", "textDisplay": "The series died an hour  after this song stopped playing. RIP", "textOriginal": "The series died an hour  after this song stopped playing. RIP", "authorDisplayName": "NetConsole", "authorProfileImageUrl": "https://yt3.ggpht.com/a/AATXAJxEqszzER71UO2L_JoMhf7IaVus3ZOKWgtBAg=s48-c-k-c0xffffffff-no-rj-mo", "authorChannelUrl": "http://www.youtube.com/channel/UCYVftGfbpf1UyU5oMn130RA", "authorChannelId": {"value": "UCYVftGfbpf1UyU5oMn130RA"}, "canRate": true, "viewerRating": "none", "likeCount": 0, "publishedAt": "2016-06-29T23:41:23Z", "updatedAt": "2016-06-29T23:41:23Z"}}, "canReply": true, "totalReplyCount": 0, "isPublic": true}}, {"kind": "youtube#commentThread", "etag": "qKkMliJbDcpCR9kgLGFk1ORu7N0", "id": "Ugi6PCaakvgkq3gCoAEC", "snippet": {"videoId": "718qcWPzvAY", "topLevelComment": {"kind": "youtube#comment", "etag": "5Zg_RZ7DxHmhyCe672fnNm2AOFI", "id": "Ugi6PCaakvgkq3gCoAEC", "snippet": {"videoId": "718qcWPzvAY", "textDisplay": "Super Paper Mario was still an RPG at heart, but instead of being turn-based, it was an Action RPG. Which I actually really approve of because the Mario platforming gameplay is better integrated, and it was also exciting.", "textOriginal": "Super Paper Mario was still an RPG at heart, but instead of being turn-based, it was an Action RPG. Which I actually really approve of because the Mario platforming gameplay is better integrated, and it was also exciting.", "authorDisplayName": "Medal Melodies", "authorProfileImageUrl": "https://yt3.ggpht.com/a/AATXAJzOgDFB_ZFMScT6q9PxuT1zYlaVKJM-4iwsX5jB1g=s48-c-k-c0xffffffff-no-rj-mo", "authorChannelUrl": "http://www.youtube.com/channel/UCnMs6kzfhudtYyn8uNTzIbw", "authorChannelId": {"value": "UCnMs6kzfhudtYyn8uNTzIbw"}, "canRate": true, "viewerRating": "none", "likeCount": 6, "publishedAt": "2016-06-29T23:41:22Z", "updatedAt": "2016-06-29T23:41:22Z"}}, "canReply": true, "totalReplyCount": 3, "isPublic": true}, "replies": {"comments": [{"kind": "youtube#comment", "etag": "PKt5pTh4bOAvnffVGJVCkOXkgz0", "id": "Ugi6PCaakvgkq3gCoAEC.8FiyL4uk6k-8V8WWhRQ82J", "snippet": {"textDisplay": "Medal Melodies I think you mean Throwback Galaxy from Mario Galaxy 2?", "textOriginal": "Medal Melodies I think you mean Throwback Galaxy from Mario Galaxy 2?", "parentId": "Ugi6PCaakvgkq3gCoAEC", "authorDisplayName": "Recht_voor_zijn_raap", "authorProfileImageUrl": "https://yt3.ggpht.com/a/AATXAJxZlwRLRQwESQuvoaszn-P9Hd-JRun7hLdUYWCuYQ=s48-c-k-c0xffffffff-no-rj-mo", "authorChannelUrl": "http://www.youtube.com/channel/UCX57ZxCliKNhpy4-Zjiv1dA", "authorChannelId": {"value": "UCX57ZxCliKNhpy4-Zjiv1dA"}, "canRate": true, "viewerRating": "none", "likeCount": 0, "publishedAt": "2017-07-18T02:59:57Z", "updatedAt": "2017-07-18T02:59:57Z"}}, {"kind": "youtube#comment", "etag": "RQBa-i-Y8ZFEgd3HPhROlbWwyoo", "id": "Ugi6PCaakvgkq3gCoAEC.8FiyL4uk6k-8J_k4e_T8u2", "snippet": {"textDisplay": "Same. I don't mind it that way, although the RPG form fits as well", "textOriginal": "Same. I don't mind it that way, although the RPG form fits as well", "parentId": "Ugi6PCaakvgkq3gCoAEC", "authorDisplayName": "Romario Desrosier", "authorProfileImageUrl": "https://yt3.ggpht.com/a/AATXAJwK4xjukVZYaiy7PnVR9-4NoKtoDDRSU97dnFr0IA=s48-c-k-c0xffffffff-no-rj-mo", "authorChannelUrl": "http://www.youtube.com/channel/UCwzozLGsq1LRDQXGSE2aoMQ", "authorChannelId": {"value": "UCwzozLGsq1LRDQXGSE2aoMQ"}, "canRate": true, "viewerRating": "none", "likeCount": 0, "publishedAt": "2016-10-03T19:49:12Z", "updatedAt": "2016-10-03T19:49:12Z"}}, {"kind": "youtube#comment", "etag": "UGzbiORPke6enZi8vriSzePOeCs", "id": "Ugi6PCaakvgkq3gCoAEC.8FiyL4uk6k-8J9WBO-2Mwl", "snippet": {"textDisplay": "Agreeeeeed. I actually wouldn't mind another Paper Mario game in SPM's style.", "textOriginal": "Agreeeeeed. I actually wouldn't mind another Paper Mario game in SPM's style.", "parentId": "Ugi6PCaakvgkq3gCoAEC", "authorDisplayName": "Colton Riffle", "authorProfileImageUrl": "https://yt3.ggpht.com/a/AATXAJxmV4Bs-jysTW3ZjmwQpAx2yXh4vxfOb-Y9bZkoSw=s48-c-k-c0xffffffff-no-rj-mo", "authorChannelUrl": "http://www.youtube.com/channel/UCs6yebl8CFQAdXmMzeBdCzg", "authorChannelId": {"value": "UCs6yebl8CFQAdXmMzeBdCzg"}, "canRate": true, "viewerRating": "none", "likeCount": 0, "publishedAt": "2016-09-23T05:59:33Z", "updatedAt": "2016-09-23T05:59:33Z"}}]}}, {"kind": "youtube#commentThread", "etag": "3ZA1x8NI5gbdup4LH_rbO0DYuW8", "id": "UgjqK2mLUzNvhngCoAEC", "snippet": {"videoId": "718qcWPzvAY", "topLevelComment": {"kind": "youtube#comment", "etag": "LkFwjKWhdJwJmKJfLGdJ1ItVrNM", "id": "UgjqK2mLUzNvhngCoAEC", "snippet": {"videoId": "718qcWPzvAY", "textDisplay": "One of my favorite tracks in the game!\nLots of suspense!", "textOriginal": "One of my favorite tracks in the game!\nLots of suspense!", "authorDisplayName": "Doughboy123x", "authorProfileImageUrl": "https://yt3.ggpht.com/a/AATXAJwLzr6YC-A6AIh4-Z7bAg7lyzTQ4PMiVnRkpWj_=s48-c-k-c0xffffffff-no-rj-mo", "authorChannelUrl": "http://www.youtube.com/channel/UCInb77ZP6dCEGgRW3B5Xazg", "authorChannelId": {"value": "UCInb77ZP6dCEGgRW3B5Xazg"}, "canRate": true, "viewerRating": "none", "likeCount": 0, "publishedAt": "2016-06-29T23:32:49Z", "updatedAt": "2016-06-29T23:32:49Z"}}, "canReply": true, "totalReplyCount": 0, "isPublic": true}}, {"kind": "youtube#commentThread", "etag": "lo2q-CIyHhRFKOcmUmj3P-FUUXU", "id": "UgjsTBE32NUShXgCoAEC", "snippet": {"videoId": "718qcWPzvAY", "topLevelComment": {"kind": "youtube#comment", "etag": "A-CBnQ18I2Po1GUePVst-8IxM10", "id": "UgjsTBE32NUShXgCoAEC", "snippet": {"videoId": "718qcWPzvAY", "textDisplay": "Welcome back to Castle Bleck, Lord Commander (OK, that was too easy). Color Splash looks quite intriguing, though you have to be cautiously excited after Sticker Star's disappointment. I'm still not sure I understand why they decided to move away from many of the series' RPG elements after TTYD, starting with this game. I do have to say that I absolutely loved Super Paper Mario, so it's not necessarily a negative.", "textOriginal": "Welcome back to Castle Bleck, Lord Commander (OK, that was too easy). Color Splash looks quite intriguing, though you have to be cautiously excited after Sticker Star's disappointment. I'm still not sure I understand why they decided to move away from many of the series' RPG elements after TTYD, starting with this game. I do have to say that I absolutely loved Super Paper Mario, so it's not necessarily a negative.", "authorDisplayName": "SupraDarky", "authorProfileImageUrl": "https://yt3.ggpht.com/a/AATXAJz-WP37CKyRsSGpodj0KF2a556urv8yhxQQEuPB=s48-c-k-c0xffffffff-no-rj-mo", "authorChannelUrl": "http://www.youtube.com/channel/UC6iBH7Pmiinoe902-JqQ7aQ", "authorChannelId": {"value": "UC6iBH7Pmiinoe902-JqQ7aQ"}, "canRate": true, "viewerRating": "none", "likeCount": 32, "publishedAt": "2016-06-29T23:28:01Z", "updatedAt": "2016-06-29T23:28:01Z"}}, "canReply": true, "totalReplyCount": 4, "isPublic": true}, "replies": {"comments": [{"kind": "youtube#comment", "etag": "qO69ge_HmV6RC-TOgZLx1UllFfI", "id": "UgjsTBE32NUShXgCoAEC.8FiwoHOSoOQ8J12lWwR2a8", "snippet": {"textDisplay": "When Sticker Star was made, Shigeru Miyamoto said that they should focus on gameplay and not story fr handheld games. Imo there are  two big things with saying this: the gameplay in Sticker Star is the least good in the series (still enjoyable, but not as enjoyable), and turn based games need to be interesting to keep the player interested. When they removed the story and all of the characters, and replaced everything with generic toads, Sticker Star kinda lost this.\n\nThat being said, Sticker Star is good, but the least good in the series.", "textOriginal": "When Sticker Star was made, Shigeru Miyamoto said that they should focus on gameplay and not story fr handheld games. Imo there are  two big things with saying this: the gameplay in Sticker Star is the least good in the series (still enjoyable, but not as enjoyable), and turn based games need to be interesting to keep the player interested. When they removed the story and all of the characters, and replaced everything with generic toads, Sticker Star kinda lost this.\n\nThat being said, Sticker Star is good, but the least good in the series.", "parentId": "UgjsTBE32NUShXgCoAEC", "authorDisplayName": "Eirian Odalis", "authorProfileImageUrl": "https://yt3.ggpht.com/a/AATXAJxnFVPquEbxzSQusCupO6lVeKKSnrVzR1aizVqS=s48-c-k-c0xffffffff-no-rj-mo", "authorChannelUrl": "http://www.youtube.com/channel/UC1aGPFAMbPS0lRf106rkEEg", "authorChannelId": {"value": "UC1aGPFAMbPS0lRf106rkEEg"}, "canRate": true, "viewerRating": "none", "likeCount": 0, "publishedAt": "2016-09-19T23:08:33Z", "updatedAt": "2016-09-19T23:08:33Z"}}, {"kind": "youtube#comment", "etag": "vqJunOUoAa_ibBJv5c85_Byyc9w", "id": "UgjsTBE32NUShXgCoAEC.8FiwoHOSoOQ8FkD3Uzkt3O", "snippet": {"textDisplay": "@Nuahsy It's not worth my \u00a38/$11", "textOriginal": "@Nuahsy It's not worth my \u00a38/$11", "parentId": "UgjsTBE32NUShXgCoAEC", "authorDisplayName": "Bainbridge", "authorProfileImageUrl": "https://yt3.ggpht.com/a/AATXAJyADUbz4MVvthvc44HpIlskVAYJ3-cUyM7RL2yEfg=s48-c-k-c0xffffffff-no-rj-mo", "authorChannelUrl": "http://www.youtube.com/channel/UCs4zlFmSDvWynnwwTCM9TTQ", "authorChannelId": {"value": "UCs4zlFmSDvWynnwwTCM9TTQ"}, "canRate": true, "viewerRating": "none", "likeCount": 0, "publishedAt": "2016-06-30T11:18:00Z", "updatedAt": "2016-06-30T11:18:00Z"}}, {"kind": "youtube#comment", "etag": "agGc6tc8G8dSVgCPYcd6SwWl7TY", "id": "UgjsTBE32NUShXgCoAEC.8FiwoHOSoOQ8FjCwKt_3pa", "snippet": {"textDisplay": "It started when Miyamoto told them (when they started making Super PM) that he wanted them to try new stuff and innovate instead of just keeping the TTYD gameplay.  Recently when asked about the removal of rpg stuff, the director said that Nintendo already has the Mario & Luigi series for the traditional RPG elements (though it's not a good reason in my opinion, but it's what she said).", "textOriginal": "It started when Miyamoto told them (when they started making Super PM) that he wanted them to try new stuff and innovate instead of just keeping the TTYD gameplay.  Recently when asked about the removal of rpg stuff, the director said that Nintendo already has the Mario & Luigi series for the traditional RPG elements (though it's not a good reason in my opinion, but it's what she said).", "parentId": "UgjsTBE32NUShXgCoAEC", "authorDisplayName": "Phenom Uprising", "authorProfileImageUrl": "https://yt3.ggpht.com/a/AATXAJzM_ZmSIaoxqDBU5Bx4tEWITkyFfVKA2a9iOMIL=s48-c-k-c0xffffffff-no-rj-mo", "authorChannelUrl": "http://www.youtube.com/channel/UCDPgzpYFGFu4j3bM6L5ifkw", "authorChannelId": {"value": "UCDPgzpYFGFu4j3bM6L5ifkw"}, "canRate": true, "viewerRating": "none", "likeCount": 5, "publishedAt": "2016-06-30T01:57:39Z", "updatedAt": "2016-06-30T01:57:39Z"}}, {"kind": "youtube#comment", "etag": "7xY4qhsPtS1ykt514DxZRdODa1A", "id": "UgjsTBE32NUShXgCoAEC.8FiwoHOSoOQ8FiyGTOOq4E", "snippet": {"textDisplay": "I mean Super Paper Mario was great all it tried  to do was put the MARIO in Paper MARIO, and imo it succeeded in blending the two... then sticker star and now colour splash have taken up the route of trail and error bosses where you use an item to instantly win and I dunno why at all other than to make it unnecessarily gimmicky.\n\nThat being said this is some Awesome music!", "textOriginal": "I mean Super Paper Mario was great all it tried  to do was put the MARIO in Paper MARIO, and imo it succeeded in blending the two... then sticker star and now colour splash have taken up the route of trail and error bosses where you use an item to instantly win and I dunno why at all other than to make it unnecessarily gimmicky.\n\nThat being said this is some Awesome music!", "parentId": "UgjsTBE32NUShXgCoAEC", "authorDisplayName": "Bainbridge", "authorProfileImageUrl": "https://yt3.ggpht.com/a/AATXAJyADUbz4MVvthvc44HpIlskVAYJ3-cUyM7RL2yEfg=s48-c-k-c0xffffffff-no-rj-mo", "authorChannelUrl": "http://www.youtube.com/channel/UCs4zlFmSDvWynnwwTCM9TTQ", "authorChannelId": {"value": "UCs4zlFmSDvWynnwwTCM9TTQ"}, "canRate": true, "viewerRating": "none", "likeCount": 4, "publishedAt": "2016-06-29T23:40:44Z", "updatedAt": "2016-06-29T23:40:44Z"}}]}}]